pydev/__init__.py
pydev/cities.py
pydev_sample-0.3.0.data/scripts/city_summary
pydev_sample-0.3.0.data/scripts/compare_cities
pydev_sample-0.3.0.dist-info/LICENSE
pydev_sample-0.3.0.dist-info/METADATA
pydev_sample-0.3.0.dist-info/WHEEL
pydev_sample-0.3.0.dist-info/top_level.txt
pydev_sample-0.3.0.dist-info/RECORD
