Metadata-Version: 2.1
Name: pydev-sample
Version: 0.3.0
Summary: Sample package to illustrate Python development
Home-page: https://github.com/mortonne/pydev_sample
Author: Neal Morton
Author-email: mortonne@gmail.com
License: UNKNOWN
Platform: UNKNOWN
Classifier: Programming Language :: Python :: 3
Classifier: License :: OSI Approved :: GNU General Public License v3 (GPLv3)
Classifier: Operating System :: OS Independent
Requires-Python: >=3.6
Requires-Dist: numpy
Requires-Dist: scipy
Requires-Dist: pandas
Requires-Dist: wikipedia
Requires-Dist: tensorflow
Requires-Dist: tensorflow-hub
Requires-Dist: pytest
